sphinxcontrib/ads/__init__.py
sphinxcontrib/ads/directives.py
sphinxcontrib/ads/errors.py
sphinxcontrib/ads/events.py
sphinxcontrib/ads/nodes.py
sphinxcontrib/ads/_templates/carbonads.html
sphinxcontrib/ads/_templates/ethicalads.html
sphinxcontrib_ads-1.0.0.dev2.dist-info/LICENSE
sphinxcontrib_ads-1.0.0.dev2.dist-info/METADATA
sphinxcontrib_ads-1.0.0.dev2.dist-info/WHEEL
sphinxcontrib_ads-1.0.0.dev2.dist-info/top_level.txt
sphinxcontrib_ads-1.0.0.dev2.dist-info/RECORD
